{
    "stats": {
        "hostname": {
            "key": "/mgmt/tm/sys/global-settings::hostname",
            "normalize": null,
            "convertArrayToMap": null,
            "filterKeys": null,
            "renameKeys": null
        },
        "version": {
            "key": "/mgmt/tm/sys/version::sys/version/0::Version"
        },
        "versionBuild": {
            "key": "/mgmt/tm/sys/version::sys/version/0::Build"
        },
        "versionSequence": {
            "key": "sequenceFromBash::commandResult"
        },
        "location": {
            "key": "/mgmt/tm/cm/device::items::{{HOSTNAME}}::location",
            "convertArrayToMap": { "keyName": "name" }
        },
        "description": {
            "key": "/mgmt/tm/cm/device::items::{{HOSTNAME}}::description",
            "convertArrayToMap": { "keyName": "name" }
        },
        "marketingName": {
            "key": "/mgmt/tm/cm/device::items::{{HOSTNAME}}::marketingName",
            "convertArrayToMap": { "keyName": "name" }
        },
        "platformId": {
            "key": "/mgmt/tm/cm/device::items::{{HOSTNAME}}::platformId",
            "convertArrayToMap": { "keyName": "name" }
        },
        "chassisId": {
            "key": "/mgmt/tm/cm/device::items::{{HOSTNAME}}::chassisId",
            "convertArrayToMap": { "keyName": "name" }
        },
        "baseMac": {
            "key": "/mgmt/tm/sys/hardware::sys/hardware/platform::sys/hardware/platform/0::baseMac"
        },
        "configReady": {
            "key": "/mgmt/tm/sys/ready::sys/ready/0::configReady"
        },
        "licenseReady": {
            "key": "/mgmt/tm/sys/ready::sys/ready/0::licenseReady"
        },
        "provisionReady": {
            "key": "/mgmt/tm/sys/ready::sys/ready/0::provisionReady"
        },
        "syncMode": {
            "key": "/mgmt/tm/cm/sync-status::cm/sync-status/0::mode"
        },
        "syncColor": {
            "key": "/mgmt/tm/cm/sync-status::cm/sync-status/0::color"
        },
        "syncStatus": {
            "key": "/mgmt/tm/cm/sync-status::cm/sync-status/0::status"
        },
        "syncSummary": {
            "key": "/mgmt/tm/cm/sync-status::cm/sync-status/0::summary"
        },
        "failoverStatus": {
            "key": "/mgmt/tm/cm/failover-status::cm/failover-status/0::status"
        },
        "failoverColor": {
            "key": "/mgmt/tm/cm/failover-status::cm/failover-status/0::color"
        },
        "cpu": {
            "key": "/mgmt/tm/sys/host-info::sys/host-info/0::sys/hostInfo/0/cpuInfo",
            "filterKeys": [ "/cpuInfo", "fiveSecAvgRatio", "oneMinAvgUser", "oneMinAvgSystem" ],
            "renameKeys": { "/cpuInfo": { "pattern": "cpuInfo\/(.*)", "group": 1 } }
        },
        "memory": {
            "key": "/mgmt/tm/sys/memory::sys/memory/memory-host::sys/memory/memory-host/0",
            "filterKeys": [ "memoryTotal", "memoryFree", "tmmMemoryTotal", "tmmMemoryFree" ]
        },
        "provisionState": {
            "key": "/mgmt/tm/sys/provision::items",
            "convertArrayToMap": { "keyName": "name", "keyNamePrefix": "name/" },
            "filterKeys": [ "name/", "level" ],
            "renameKeys": { "name/": { "pattern": "name\/(.*)", "group": 1 } }
        },
        "networkInterfaces": {
            "key": "/mgmt/tm/net/interface/stats",
            "filterKeys": [ "/stats", "counters.bitsIn", "counters.bitsOut" ],
            "renameKeys": { "net/interface": "([0-9]\\.[0-9]|(?!\/)mgmt(?=\/))" }
        },
        "tmmCpu": {
            "key": "/mgmt/tm/sys/tmm-info",
            "filterKeys": [ "/tmm-info", "oneMinAvgUsageRatio" ],
            "renameKeys": { "sys/tmm-info": "([0-9]\\.[0-9])" }
        },
        "tmmTraffic": {
            "key": "/mgmt/tm/sys/tmm-traffic",
            "filterKeys": [ "/tmm-traffic", "clientSideTraffic.bitsIn", "clientSideTraffic.bitsOut", "clientSideTraffic.pktsIn", "clientSideTraffic.pktsOut" ],
            "renameKeys": { "sys/tmm-traffic": "([0-9]\\.[0-9])" }
        },
        "virtualServerStats": {
            "key": "/mgmt/tm/ltm/virtual/stats",
            "filterKeys": [ "/stats", "clientside.bitsIn", "clientside.bitsOut", "clientside.pktsIn", "clientside.pktsOut", "clientside.curConns", "availabilityState",  "enabledState", "destination" ],
            "renameKeys": { "ltm/virtual": { "pattern": "virtual\/(.*)\/", "group": 1 } }
        },
        "poolStats": {
            "key": "/mgmt/tm/ltm/pool/stats",
            "filterKeys": [ "/stats", "serverside.bitsIn", "serverside.bitsOut", "serverside.pktsIn", "serverside.pktsOut", "serverside.curConns", "availabilityState",  "enabledState" ],
            "renameKeys": { "ltm/pool": { "pattern": "pool\/(.*)\/", "group": 1 } }
        }
    },
    "context": {
        "HOSTNAME": {
            "key": "/mgmt/tm/sys/global-settings::hostname"
        }
    }
}