{
    "stats": {
        "version": {
            "key": "/mgmt/tm/sys/version::sys/version/0::Version::description"
        },
        "configReady": {
            "key": "/mgmt/tm/sys/ready::sys/ready/0::configReady::description"
        },
        "licenseReady": {
            "key": "/mgmt/tm/sys/ready::sys/ready/0::licenseReady::description"
        },
        "provisionReady": {
            "key": "/mgmt/tm/sys/ready::sys/ready/0::provisionReady::description"
        },
        "syncStatus": {
            "key": "/mgmt/tm/cm/sync-status::cm/sync-status/0::color::description"
        },
        "failoverStatus": {
            "key": "/mgmt/tm/cm/failover-status::cm/failover-status/0::color::description"
        },
        "netInterfaceStats": {
            "key": "/mgmt/tm/net/interface/stats"
        },
        "tmmInfo": {
            "key": "/mgmt/tm/sys/tmm-info"
        },
        "tmmTraffic": {
            "key": "/mgmt/tm/sys/tmm-traffic"
        },
        "virtualServerStats": {
            "key": "/mgmt/tm/ltm/virtual/stats"
        }
    }
}